{"name":"Katari Extensions","badgeLabel":"katari-ext","signingKey":"cd5497fb5905f39b0233a1e6839e44cffb690f4e34f2046a39dc9bff0df0a4d2","contact":{"website":"https://github.com/katariapp/katari-extensions"},"extensionList":{"extensions":[{"name":"Katari: Rezka","packageName":"eu.kanade.tachiyomi.extension.all.rezka","resources":{"apkUrl":"https://raw.githubusercontent.com/katariapp/katari-extensions/repo/apk/rezka.apk","iconUrl":"https://raw.githubusercontent.com/katariapp/katari-extensions/repo/icon/eu.kanade.tachiyomi.extension.all.rezka.png"},"extensionLib":"2.0","versionCode":16,"versionName":"2.0.6","contentWarning":"CONTENT_WARNING_SAFE","sources":[{"id":500000001,"name":"Rezka Films","language":"ru","homeUrl":"https://rezka.ag/films","supportedEntryTypes":["ANIME"]},{"id":500000002,"name":"Rezka Series","language":"ru","homeUrl":"https://rezka.ag/series","supportedEntryTypes":["ANIME"]},{"id":500000003,"name":"Rezka Cartoons","language":"ru","homeUrl":"https://rezka.ag/cartoons","supportedEntryTypes":["ANIME"]},{"id":500000004,"name":"Rezka Anime","language":"ru","homeUrl":"https://rezka.ag/anime","supportedEntryTypes":["ANIME"]}]},{"name":"Katari: Project Gutenberg","packageName":"eu.kanade.tachiyomi.extension.en.gutenberg","resources":{"apkUrl":"https://raw.githubusercontent.com/katariapp/katari-extensions/repo/apk/gutenberg.apk","iconUrl":"https://raw.githubusercontent.com/katariapp/katari-extensions/repo/icon/eu.kanade.tachiyomi.extension.en.gutenberg.png"},"extensionLib":"2.1","versionCode":1,"versionName":"2.1.0","contentWarning":"CONTENT_WARNING_SAFE","sources":[{"id":500000005,"name":"Project Gutenberg","language":"en","homeUrl":"https://www.gutenberg.org","supportedEntryTypes":["BOOK"]}]},{"name":"Katari: NovelArrow","packageName":"eu.kanade.tachiyomi.extension.en.novelarrow","resources":{"apkUrl":"https://raw.githubusercontent.com/katariapp/katari-extensions/repo/apk/novelarrow.apk","iconUrl":"https://raw.githubusercontent.com/katariapp/katari-extensions/repo/icon/eu.kanade.tachiyomi.extension.en.novelarrow.png"},"extensionLib":"2.1","versionCode":1,"versionName":"2.1.0","contentWarning":"CONTENT_WARNING_NSFW","sources":[{"id":500000006,"name":"NovelArrow","language":"en","homeUrl":"https://novelarrow.com","supportedEntryTypes":["BOOK"]}]},{"name":"Katari: NovelBuddy","packageName":"eu.kanade.tachiyomi.extension.en.novelbuddy","resources":{"apkUrl":"https://raw.githubusercontent.com/katariapp/katari-extensions/repo/apk/novelbuddy.apk","iconUrl":"https://raw.githubusercontent.com/katariapp/katari-extensions/repo/icon/eu.kanade.tachiyomi.extension.en.novelbuddy.png"},"extensionLib":"2.1","versionCode":1,"versionName":"2.1.0","contentWarning":"CONTENT_WARNING_NSFW","sources":[{"id":500000007,"name":"NovelBuddy","language":"en","homeUrl":"https://novelbuddy.me","supportedEntryTypes":["BOOK"]}]}]}}
